Workbook

Sheet 1. Assumptions
B2: Tab 1 — ASSUMPTIONS / Giả định đầu vào
B3: Luật chơi: chỉ điền vào các ô MÀU VÀNG. Các ô khác là công thức và sẽ tự tính.
B5: 1. Product & Pricing / Sản phẩm & Giá
C6: Optimistic | D6: Base | E6: Pessimistic | F6: Đơn vị | G6: Ghi chú / Note
B7: ARPU — Giá bán bình quân/khách/tháng | C7: 12000000 | D7: 10500000 | E7: 8000000 | F7: VND | G7: Hybrid B2B: phí nền tảng + phí usage; ARPU Base bình quân 10,5 triệu/showroom/tháng
B8: Adoption rate — % TAM chuyển thành khách/tháng | C8: 0.005 | D8: 0.003 | E8: 0.001 | F8: %/tháng | G8: Tỷ lệ địa điểm trong TAM bắt đầu trả phí mới mỗi tháng: 0,5% / 0,3% / 0,1%, đúng dải của brief
B9: Total addressable market (số khách tiềm năng) | C9: 10000 | D9: 10000 | E9: 10000 | F9: khách | G9: Planning TAM 10.000 điểm bán ô tô tại Đông Nam Á; VinFast là beachhead, không phải toàn bộ TAM
B11: 2. COGS / Chi phí biến đổi trên mỗi khách hàng
B12: API cost / khách / tháng | C12: 1200000 | D12: 1500000 | E12: 2000000 | F12: VND | G12: Ngân sách model API/tool calls phân bổ theo một showroom mỗi tháng
B13: Hidden costs (labeling, retraining, QA) | C13: 1200000 | D13: 1300000 | E13: 1700000 | F13: VND | G13: Labeling, retraining, human QA, monitoring và compliance; luôn > 30% API cost
B14: Infrastructure (server/cloud) / khách | C14: 1100000 | D14: 1200000 | E14: 1300000 | F14: VND | G14: Cloud, storage, observability và integration phân bổ theo showroom
B15: → Tổng COGS / khách / tháng | C15: =C12+C13+C14 -> 3500000 | D15: =D12+D13+D14 -> 4000000 | E15: =E12+E13+E14 -> 5000000
B17: 3. Customer Behavior / Hành vi khách hàng
B18: Monthly Churn Rate — % khách rời mỗi tháng | C18: 0.02 | D18: 0.03 | E18: 0.045 | F18: % | G18: Base 3%/tháng để thận trọng; Pessimistic = 1,5x Base
B19: → Số tháng ở lại trung bình | C19: =IFERROR(1/C18,0) -> 50 | D19: =IFERROR(1/D18,0) -> 33.333333 | E19: =IFERROR(1/E18,0) -> 22.222222
B21: 4. Sales & Marketing / Chi phí thu hút khách
B22: CAC — Tổng chi phí có 1 khách hàng mới | C22: 40000000 | D22: 45000000 | E22: 67500000 | F22: VND | G22: Targeted enterprise sales qua mạng lưới đại lý; Pessimistic = 1,5x Base
B24: 5. Fixed Costs / Chi phí cố định hàng tháng
B25: Salaries — Lương team (PM/Dev/Designer) | C25: 120000000 | D25: 120000000 | E25: 120000000 | F25: VND/tháng | G25: Pessimistic giữ nguyên core team; Plan B cắt rollout và chi phí không thiết yếu
B26: Office, tools, admin | C26: 20000000 | D26: 20000000 | E26: 15000000 | F26: VND/tháng | G26: Pessimistic cắt tool/ops không thiết yếu ngay khi trigger xuất hiện
B27: Marketing budget hàng tháng | C27: 10000000 | D27: 10000000 | E27: 5000000 | F27: VND/tháng | G27: Brand/content baseline; CAC tại dòng 22 đã bao gồm chi phí acquisition theo khách mới
B28: → Tổng Fixed Cost / tháng | C28: =SUM(C25:C27) -> 150000000 | D28: =SUM(D25:D27) -> 150000000 | E28: =SUM(E25:E27) -> 140000000
B30: 6. Initial Investment / Vốn đầu tư ban đầu
B31: Vốn đầu tư ban đầu (build MVP, setup) | C31: 700000000 | D31: 600000000 | E31: 800000000 | F31: VND | G31: Chi phí một lần cho integration, hardening, security và rollout
B32: Tiền mặt ban đầu (sau khi đã trừ vốn đầu tư) | C32: 10000000000 | D32: 10000000000 | E32: 10000000000 | F32: VND | G32: Mô hình yêu cầu cam kết 10 tỷ VND tiền mặt để kịch bản xấu vẫn có runway trên 12 tháng
B34: 7. Discount Rate / Tỷ suất chiết khấu (cho NPV)
B35: Annual discount rate (WACC) | C35: 0.18 | D35: 0.22 | E35: 0.25 | F35: %/năm | G35: WACC tăng theo mức rủi ro của từng kịch bản
B36: → Monthly discount rate | C36: =(1+C35)^(1/12)-1 -> 0.01388843 | D36: =(1+D35)^(1/12)-1 -> 0.016708964 | E36: =(1+E35)^(1/12)-1 -> 0.018769265
B38: 8. Decision Note / Ghi chú quyết định
B39: ViVi dùng hybrid pricing B2B: phí nền tảng 9 triệu VND/showroom/tháng cộng usage bình quân 1,5 triệu, nên ARPU Base là 10,5 triệu. TAM dùng cho bài là 10.000 điểm bán ô tô tại Đông Nam Á; mạng lưới VinFast là nhóm khách hàng đầu tiên. Adoption 0,3%/tháng ở Base tương đương 30 điểm bán mới. Với gross margin 61,9%, LTV/CAC đạt 4,81x và payback 6,9 tháng. Pessimistic hạ adoption còn 0,1%, tăng churn và CAC lên 1,5x Base; 10 tỷ VND tiền mặt giữ runway 14 tháng để nhóm có thời gian cắt scope.

Sheet 2. Unit Economics
B2: Tab 2 — UNIT ECONOMICS / Kinh tế đơn vị
B3: Tự động tính từ Tab 1. Kiểm tra: LTV/CAC > 3 (Base) và CAC Payback < 12 tháng.
B5: Chỉ số | C5: Optimistic | D5: Base | E5: Pessimistic | F5: Đơn vị | G5: Benchmark / Note
B7: Trên mỗi khách hàng / per customer
B8: ARPU / tháng | C8: ='1. Assumptions'!C7 -> 12000000 | D8: ='1. Assumptions'!D7 -> 10500000 | E8: ='1. Assumptions'!E7 -> 8000000 | F8: VND | G8: Liên kết từ Tab Assumptions
B9: COGS / tháng | C9: ='1. Assumptions'!C15 -> 3500000 | D9: ='1. Assumptions'!D15 -> 4000000 | E9: ='1. Assumptions'!E15 -> 5000000 | F9: VND
B10: → Gross Profit / tháng | C10: =C8-C9 -> 8500000 | D10: =D8-D9 -> 6500000 | E10: =E8-E9 -> 3000000
B11: → Gross Margin % | C11: =IFERROR(C10/C8,0) -> 0.70833333 | D11: =IFERROR(D10/D8,0) -> 0.61904762 | E11: =IFERROR(E10/E8,0) -> 0.375 | G11: AI product target: 40-60%. SaaS truyền thống: 80%+
B13: LTV — Customer Lifetime Value
B14: Số tháng ở lại trung bình | C14: ='1. Assumptions'!C19 -> 50 | D14: ='1. Assumptions'!D19 -> 33.333333 | E14: ='1. Assumptions'!E19 -> 22.222222 | F14: tháng
B15: → LTV = Gross Profit × Số tháng ở lại | C15: =C10*C14 -> 425000000 | D15: =D10*D14 -> 2.1666667e+08 | E15: =E10*E14 -> 66666667 | G15: Tổng lợi nhuận gộp một khách mang lại trong vòng đời
B17: CAC — Customer Acquisition Cost
B18: CAC — Chi phí thu hút 1 khách | C18: ='1. Assumptions'!C22 -> 40000000 | D18: ='1. Assumptions'!D22 -> 45000000 | E18: ='1. Assumptions'!E22 -> 67500000 | F18: VND
B20: Key Ratios / Tỷ lệ then chốt
B21: → LTV / CAC Ratio | C21: =IFERROR(C15/C18,0) -> 10.625 | D21: =IFERROR(D15/D18,0) -> 4.8148148 | E21: =IFERROR(E15/E18,0) -> 0.98765432 | G21: 🎯 Target > 3.0x (tiêu chuẩn vàng VC)
B22: → CAC Payback Period | C22: =IFERROR(C18/C10,0) -> 4.7058824 | D22: =IFERROR(D18/D10,0) -> 6.9230769 | E22: =IFERROR(E18/E10,0) -> 22.5 | G22: 🎯 Target < 12 tháng (early-stage)
B24: Verdict / Kết luận
B25: Unit Economics Status | C25: =IF(AND(C21>=3,C22<=12),"✓ HEALTHY",IF(OR(C21<1,C22>18),"✗ UNHEALTHY","⚠ WATCH")) -> ✓ HEALTHY | D25: =IF(AND(D21>=3,D22<=12),"✓ HEALTHY",IF(OR(D21<1,D22>18),"✗ UNHEALTHY","⚠ WATCH")) -> ✓ HEALTHY | E25: =IF(AND(E21>=3,E22<=12),"✓ HEALTHY",IF(OR(E21<1,E22>18),"✗ UNHEALTHY","⚠ WATCH")) -> ✗ UNHEALTHY
B28: BONUS — Sensitivity Analysis: LTV/CAC theo ARPU và Churn (Base COGS & CAC)
B29: Mỗi ô là LTV/CAC; dùng COGS Base và CAC Base, chỉ thay ARPU cùng churn.
B30: ARPU \ Churn | C30: 0.02 | D30: 0.025 | E30: 0.03 | F30: 0.04 | G30: 0.05
B31: 8500000 | C31: =(($B31-'1. Assumptions'!$D$15)/C30)/'1. Assumptions'!$D$22 -> 5 | D31: =(($B31-'1. Assumptions'!$D$15)/D30)/'1. Assumptions'!$D$22 -> 4 | E31: =(($B31-'1. Assumptions'!$D$15)/E30)/'1. Assumptions'!$D$22 -> 3.3333333 | F31: =(($B31-'1. Assumptions'!$D$15)/F30)/'1. Assumptions'!$D$22 -> 2.5 | G31: =(($B31-'1. Assumptions'!$D$15)/G30)/'1. Assumptions'!$D$22 -> 2
B32: 9500000 | C32: =(($B32-'1. Assumptions'!$D$15)/C30)/'1. Assumptions'!$D$22 -> 6.1111111 | D32: =(($B32-'1. Assumptions'!$D$15)/D30)/'1. Assumptions'!$D$22 -> 4.8888889 | E32: =(($B32-'1. Assumptions'!$D$15)/E30)/'1. Assumptions'!$D$22 -> 4.0740741 | F32: =(($B32-'1. Assumptions'!$D$15)/F30)/'1. Assumptions'!$D$22 -> 3.0555556 | G32: =(($B32-'1. Assumptions'!$D$15)/G30)/'1. Assumptions'!$D$22 -> 2.4444444
B33: 10500000 | C33: =(($B33-'1. Assumptions'!$D$15)/C30)/'1. Assumptions'!$D$22 -> 7.2222222 | D33: =(($B33-'1. Assumptions'!$D$15)/D30)/'1. Assumptions'!$D$22 -> 5.7777778 | E33: =(($B33-'1. Assumptions'!$D$15)/E30)/'1. Assumptions'!$D$22 -> 4.8148148 | F33: =(($B33-'1. Assumptions'!$D$15)/F30)/'1. Assumptions'!$D$22 -> 3.6111111 | G33: =(($B33-'1. Assumptions'!$D$15)/G30)/'1. Assumptions'!$D$22 -> 2.8888889
B34: 11500000 | C34: =(($B34-'1. Assumptions'!$D$15)/C30)/'1. Assumptions'!$D$22 -> 8.3333333 | D34: =(($B34-'1. Assumptions'!$D$15)/D30)/'1. Assumptions'!$D$22 -> 6.6666667 | E34: =(($B34-'1. Assumptions'!$D$15)/E30)/'1. Assumptions'!$D$22 -> 5.5555556 | F34: =(($B34-'1. Assumptions'!$D$15)/F30)/'1. Assumptions'!$D$22 -> 4.1666667 | G34: =(($B34-'1. Assumptions'!$D$15)/G30)/'1. Assumptions'!$D$22 -> 3.3333333
B35: 12500000 | C35: =(($B35-'1. Assumptions'!$D$15)/C30)/'1. Assumptions'!$D$22 -> 9.4444444 | D35: =(($B35-'1. Assumptions'!$D$15)/D30)/'1. Assumptions'!$D$22 -> 7.5555556 | E35: =(($B35-'1. Assumptions'!$D$15)/E30)/'1. Assumptions'!$D$22 -> 6.2962963 | F35: =(($B35-'1. Assumptions'!$D$15)/F30)/'1. Assumptions'!$D$22 -> 4.7222222 | G35: =(($B35-'1. Assumptions'!$D$15)/G30)/'1. Assumptions'!$D$22 -> 3.7777778
B37: MODEL CHECKS
B38: Check | C38: Actual | D38: Rule | E38: Status | F38: Where to fix | G38: Note
B39: Base LTV/CAC | C39: =D21 -> 4.8148148 | D39: 3 | E39: =IF(C39>D39,"OK","FAIL") -> OK | F39: Assumptions!D7:D22 | G39: > 3.0x
B40: Base CAC Payback | C40: =D22 -> 6.9230769 | D40: 12 | E40: =IF(C40<D40,"OK","FAIL") -> OK | F40: Assumptions!D7:D22 | G40: < 12 months
B41: Hidden/API ratio | C41: ='1. Assumptions'!D13/'1. Assumptions'!D12 -> 0.86666667 | D41: 0.3 | E41: =IF(C41>=D41,"OK","FAIL") -> OK | F41: Assumptions!D12:D13 | G41: >= 30%
B42: Pess/Base Churn | C42: ='1. Assumptions'!E18/'1. Assumptions'!D18 -> 1.5 | D42: 1.5 | E42: =IF(C42>=D42,"OK","FAIL") -> OK | F42: Assumptions!D18:E18 | G42: >= 1.5x
B43: Pess/Base CAC | C43: ='1. Assumptions'!E22/'1. Assumptions'!D22 -> 1.5 | D43: 1.5 | E43: =IF(C43>=D43,"OK","FAIL") -> OK | F43: Assumptions!D22:E22 | G43: >= 1.5x
B44: Adoption in lab range | C44: =IF(AND(MIN('1. Assumptions'!C8:E8)>=0.001,MAX('1. Assumptions'!C8:E8)<=0.005),1,0) -> 1 | D44: 1 | E44: =IF(C44=D44,"OK","FAIL") -> OK | F44: Assumptions!C8:E8 | G44: 0.1%-0.5% all cases
B45: TAM in lab range | C45: =IF(AND(MIN('1. Assumptions'!C9:E9)>=10000,MAX('1. Assumptions'!C9:E9)<=1000000),1,0) -> 1 | D45: 1 | E45: =IF(C45=D45,"OK","FAIL") -> OK | F45: Assumptions!C9:E9 | G45: 10,000-1,000,000
B46: Pessimistic runway | C46: ='3. P&L & ROI'!C40 -> 14 | D46: 12 | E46: =IF(OR(C46=">= 24",IFERROR(C46>=D46,FALSE())),"OK","FAIL") -> OK | F46: Assumptions!E25:E32 | G46: >= 12 months
B48: MODEL STATUS | E48: =IF(COUNTIF(E39:E46,"FAIL")=0,"PASS","FAIL") -> PASS

Sheet 3. P&L & ROI
B2: Tab 3 — P&L & ROI / 24 tháng
B4: Chọn scenario: | C4: Pessimistic | D4: Đổi scenario tại đây để toàn bộ P&L tự cập nhật
B6: Active scenario index: | C6: =MATCH(C4,{"Optimistic","Base","Pessimistic"},0) -> 3
B7: Selected scenario inputs ↓
B8: ARPU / khách / tháng | C8: =CHOOSE($C$6,'1. Assumptions'!C7,'1. Assumptions'!D7,'1. Assumptions'!E7) -> 8000000
B9: Adoption rate | C9: =CHOOSE($C$6,'1. Assumptions'!C8,'1. Assumptions'!D8,'1. Assumptions'!E8) -> 0.001
B10: TAM (số khách tiềm năng) | C10: =CHOOSE($C$6,'1. Assumptions'!C9,'1. Assumptions'!D9,'1. Assumptions'!E9) -> 10000
B11: Total COGS / khách | C11: =CHOOSE($C$6,'1. Assumptions'!C15,'1. Assumptions'!D15,'1. Assumptions'!E15) -> 5000000
B12: Monthly Churn Rate | C12: =CHOOSE($C$6,'1. Assumptions'!C18,'1. Assumptions'!D18,'1. Assumptions'!E18) -> 0.045
B13: CAC / khách mới | C13: =CHOOSE($C$6,'1. Assumptions'!C22,'1. Assumptions'!D22,'1. Assumptions'!E22) -> 67500000
B14: Fixed Cost / tháng | C14: =CHOOSE($C$6,'1. Assumptions'!C28,'1. Assumptions'!D28,'1. Assumptions'!E28) -> 140000000
B15: Initial Investment | C15: =CHOOSE($C$6,'1. Assumptions'!C31,'1. Assumptions'!D31,'1. Assumptions'!E31) -> 800000000
B16: Initial Cash | C16: =CHOOSE($C$6,'1. Assumptions'!C32,'1. Assumptions'!D32,'1. Assumptions'!E32) -> 10000000000
B17: Monthly Discount Rate | C17: =CHOOSE($C$6,'1. Assumptions'!C36,'1. Assumptions'!D36,'1. Assumptions'!E36) -> 0.018769265
B20: P&L Projection — 24 months (VND)
B21: Month | C21: M1 | D21: M2 | E21: M3 | F21: M4 | G21: M5 | H21: M6 | I21: M7 | J21: M8 | K21: M9 | L21: M10 | M21: M11 | N21: M12 | O21: M13 | P21: M14 | Q21: M15 | R21: M16 | S21: M17 | T21: M18 | U21: M19 | V21: M20 | W21: M21 | X21: M22 | Y21: M23 | Z21: M24 | AA21: TOTAL
B22: New customers acquired | C22: =ROUND($C$10*$C$9,0) -> 10 | D22: =ROUND($C$10*$C$9,0) -> 10 | E22: =ROUND($C$10*$C$9,0) -> 10 | F22: =ROUND($C$10*$C$9,0) -> 10 | G22: =ROUND($C$10*$C$9,0) -> 10 | H22: =ROUND($C$10*$C$9,0) -> 10 | I22: =ROUND($C$10*$C$9,0) -> 10 | J22: =ROUND($C$10*$C$9,0) -> 10 | ... Z22: =ROUND($C$10*$C$9,0) -> 10 | AA22: =SUM(C22:Z22) -> 240
B23: Active customers (end of month) | C23: =C22 -> 10 | D23: =C23*(1-$C$12)+D22 -> 19.55 | E23: =D23*(1-$C$12)+E22 -> 28.67025 | F23: =E23*(1-$C$12)+F22 -> 37.380089 | G23: =F23*(1-$C$12)+G22 -> 45.697985 | H23: =G23*(1-$C$12)+H22 -> 53.641575 | I23: =H23*(1-$C$12)+I22 -> 61.227705 | J23: =I23*(1-$C$12)+J22 -> 68.472458 | K23: =J23*(1-$C$12)+K22 -> 75.391197 | ... Z23: =Y23*(1-$C$12)+Z22 -> 148.62382
B25: Revenue | C25: =C23*$C$8 -> 80000000 | D25: =D23*$C$8 -> 156400000 | E25: =E23*$C$8 -> 229362000 | F25: =F23*$C$8 -> 299040710 | G25: =G23*$C$8 -> 3.6558388e+08 | H25: =H23*$C$8 -> 4.291326e+08 | I25: =I23*$C$8 -> 4.8982164e+08 | J25: =J23*$C$8 -> 5.4777966e+08 | ... Z25: =Z23*$C$8 -> 1.1889905e+09 | AA25: =SUM(C25:Z25) -> 1.7433645e+10
B26: COGS (variable cost) | C26: =C23*$C$11 -> 50000000 | D26: =D23*$C$11 -> 97750000 | E26: =E23*$C$11 -> 143351250 | F26: =F23*$C$11 -> 1.8690044e+08 | G26: =G23*$C$11 -> 2.2848992e+08 | H26: =H23*$C$11 -> 2.6820788e+08 | I26: =I23*$C$11 -> 3.0613852e+08 | J26: =J23*$C$11 -> 3.4236229e+08 | ... Z26: =Z23*$C$11 -> 7.4311908e+08 | AA26: =SUM(C26:Z26) -> 1.0896028e+10
B27: Gross Profit | C27: =C25-C26 -> 30000000 | D27: =D25-D26 -> 58650000 | E27: =E25-E26 -> 86010750 | F27: =F25-F26 -> 1.1214027e+08 | G27: =G25-G26 -> 1.3709395e+08 | H27: =H25-H26 -> 1.6092473e+08 | I27: =I25-I26 -> 1.8368311e+08 | J27: =J25-J26 -> 2.0541737e+08 | ... Z27: =Z25-Z26 -> 4.4587145e+08 | AA27: =SUM(C27:Z27) -> 6.537617e+09
B28: Marketing/Acquisition cost | C28: =C22*$C$13 -> 675000000 | D28: =D22*$C$13 -> 675000000 | E28: =E22*$C$13 -> 675000000 | F28: =F22*$C$13 -> 675000000 | G28: =G22*$C$13 -> 675000000 | H28: =H22*$C$13 -> 675000000 | I28: =I22*$C$13 -> 675000000 | J28: =J22*$C$13 -> 675000000 | ... Z28: =Z22*$C$13 -> 675000000 | AA28: =SUM(C28:Z28) -> 16200000000
B29: Fixed cost (salaries + ops) | C29: =$C$14 -> 140000000 | D29: =$C$14 -> 140000000 | E29: =$C$14 -> 140000000 | F29: =$C$14 -> 140000000 | G29: =$C$14 -> 140000000 | H29: =$C$14 -> 140000000 | I29: =$C$14 -> 140000000 | J29: =$C$14 -> 140000000 | ... Z29: =$C$14 -> 140000000 | AA29: =SUM(C29:Z29) -> 3360000000
B30: Operating Profit (EBITDA) | C30: =C27-C28-C29 -> -785000000 | D30: =D27-D28-D29 -> -756350000 | E30: =E27-E28-E29 -> -728989250 | F30: =F27-F28-F29 -> -7.0285973e+08 | G30: =G27-G28-G29 -> -6.7790605e+08 | H30: =H27-H28-H29 -> -6.5407527e+08 | I30: =I27-I28-I29 -> -6.3131689e+08 | J30: =J27-J28-J29 -> -6.0958263e+08 | ... Z30: =Z27-Z28-Z29 -> -3.6912855e+08 | AA30: =SUM(C30:Z30) -> -1.3022383e+10
B32: Cash Flow (after investment) | C32: =C30-$C$15 -> -1585000000 | D32: =D30 -> -756350000 | E32: =E30 -> -728989250 | F32: =F30 -> -7.0285973e+08 | G32: =G30 -> -6.7790605e+08 | H32: =H30 -> -6.5407527e+08 | I32: =I30 -> -6.3131689e+08 | J32: =J30 -> -6.0958263e+08 | K32: =K30 -> -5.8882641e+08 | ... Z32: =Z30 -> -3.6912855e+08 | AA32: =SUM(C32:Z32) -> -1.3822383e+10
B33: Cash Position (cumulative) | C33: =$C$16+C32 -> 8415000000 | D33: =C33+D32 -> 7658650000 | E33: =D33+E32 -> 6929660750 | F33: =E33+F32 -> 6.226801e+09 | G33: =F33+G32 -> 5.548895e+09 | H33: =G33+H32 -> 4.8948197e+09 | I33: =H33+I32 -> 4.2635028e+09 | J33: =I33+J32 -> 3.6539202e+09 | K33: =J33+K32 -> 3.0650938e+09 | ... Z33: =Y33+Z32 -> -3.822383e+09
B36: ROI Metrics / Chỉ số đánh giá tổng thể dự án
B37: NPV (Net Present Value, mil VND) | C37: =(NPV($C$17,D32:Z32)+C32)/1000000 -> -11713.835 | D37: ="(target: > 0)" -> (target: > 0)
B38: IRR (Annual) | C38: =IFERROR((1+IRR(C32:Z32))^12-1,0) -> 0 | D38: ="(target: > "&TEXT(CHOOSE($C$6,'1. Assumptions'!C35,'1. Assumptions'!D35,'1. Assumptions'!E35),"0.0%")&")" -> (target: > 25.0%)
B39: Project Payback (months) | C39: =IFERROR(MATCH(TRUE(),INDEX(C41:Z41>=0,0),0),"> 24") -> > 24 | D39: ="(target: < 24)" -> (target: < 24)
B40: Runway (months until cash = 0) | C40: =IFERROR(MATCH(TRUE(),INDEX(C33:Z33<0,0),0)-1,">= 24") -> 14 | D40: ="(target: >= 12)" -> (target: >= 12)
B41: (helper: cumulative cash flow) | C41: =C32 -> -1585000000 | D41: =C41+D32 -> -2341350000 | E41: =D41+E32 -> -3070339250 | F41: =E41+F32 -> -3.773199e+09 | G41: =F41+G32 -> -4.451105e+09 | H41: =G41+H32 -> -5.1051803e+09 | I41: =H41+I32 -> -5.7364972e+09 | J41: =I41+J32 -> -6.3460798e+09 | K41: =J41+K32 -> -6.9349062e+09 | ... Z41: =Y41+Z32 -> -1.3822383e+10
B43: Final Verdict / Có nên làm dự án này?
B44: Project Decision | C44: =IF(AND(C37>0,C38>CHOOSE($C$6,'1. Assumptions'!C35,'1. Assumptions'!D35,'1. Assumptions'!E35)),"✓ GO — NPV+ và IRR > WACC",IF(C37<0,"✗ NO-GO — NPV âm: dự án không tạo giá trị","⚠ HOLD — IRR thấp hơn kỳ vọng, cần điều chỉnh")) -> ✗ NO-GO — NPV âm: dự án không tạo giá trị
